api/__init__.py
api/task.py
api/user.py
resources/__init__.py
resources/tasks.json
resources/users.json
services/__init__.py
services/task.py
services/user.py
setups/__init__.py
setups/app.py
setups/config.py
setups/runapp.py
wazuh_api_rest-0.0.1.dist-info/METADATA
wazuh_api_rest-0.0.1.dist-info/WHEEL
wazuh_api_rest-0.0.1.dist-info/entry_points.txt
wazuh_api_rest-0.0.1.dist-info/top_level.txt
wazuh_api_rest-0.0.1.dist-info/RECORD
