Metadata-Version: 2.1
Name: wazuh-api-rest
Version: 0.0.1
Summary: Wazuh Api Rest
Home-page: https://github.com/pypa/sampleproject
Author: Germán Martinez
Author-email: germand_m@hotmail.com
License: UNKNOWN
Platform: UNKNOWN
Classifier: Programming Language :: Python :: 3
Classifier: License :: OSI Approved :: MIT License
Classifier: Operating System :: OS Independent
Requires-Python: >=3.9
Requires-Dist: Click (==7.1.2)
Requires-Dist: fastapi (==0.61.0)
Requires-Dist: jq (==1.2.1)
Requires-Dist: uvicorn (==0.11.8)
